README.md
setup.py
pyvianka/__init__.py
pyvianka/cal.py
viankafl.egg-info/PKG-INFO
viankafl.egg-info/SOURCES.txt
viankafl.egg-info/dependency_links.txt
viankafl.egg-info/top_level.txt