Metadata-Version: 2.1
Name: viankafl
Version: 0.1
Summary: Este es mi paquete pypi
Author: vianka
Author-email: vianka726@gmail.com
License: MIT
